<configuration>
  <!-- <property>
    <name>hbase.rootdir</name>
    <value>hdfs://master:8020/hbase</value>
  </property> -->
  <property>
    <name>hbase.rootdir</name>
    <value>file:///shared/dfs/hbase</value>
  </property>
  <property>
    <name>hbase.zookeeper.property.dataDir</name>
    <value>/zookeeper</value>
  </property>
  <property>
    <name>hbase.tmp.dir</name>
    <value>./tmp</value>
  </property>
  <property>
    <name>hbase.unsafe.stream.capability.enforce</name>
    <value>false</value>
  </property>
  <property>
    <name>hbase.cluster.distributed</name>
    <value>true</value>
  </property>
  <property>
    <name>hbase.zookeeper.quorum</name>
    <value>zoo</value>
  </property>
  <property>
    <name>hbase.zookeeper.property.clientPort</name>
    <value>2181</value>
  </property>
  <property>
    <name>zookeeper.znode.parent</name>
    <value>/hbase</value>
  </property>
  <property>
    <name>hbase.regionserver.kerberos.principal</name>
    <value>hadoop/cluster@EXAMPLE.COM</value>
  </property>
  <property>
    <name>hbase.regionserver.keytab.file</name>
    <value>/shared/keytabs/hadoop.keytab</value>
  </property>
  <property>
    <name>hbase.master.kerberos.principal</name>
    <value>hadoop/cluster@EXAMPLE.COM</value>
  </property>
  <property>
    <name>hbase.master.keytab.file</name>
    <value>/shared/keytabs/hadoop.keytab</value>
  </property>
</configuration>
